{"data":{"propertyOrder":{},"properties":{"title":{"name":"title","reference":"scalar","getter":false,"setter":false,"type":"string","array":false},"description":{"name":"description","reference":"scalar","nullable":true,"getter":false,"setter":false,"type":"string","array":false,"optional":true},"createdBy":{"name":"createdBy","reference":"m:1","cascade":["persist"],"type":"User","owner":true,"array":false}},"props":[{"name":"title","reference":"scalar","getter":false,"setter":false,"type":"string","array":false},{"name":"description","reference":"scalar","nullable":true,"getter":false,"setter":false,"type":"string","array":false,"optional":true},{"name":"createdBy","reference":"m:1","cascade":["persist"],"type":"User","owner":true,"array":false}],"primaryKeys":[],"filters":{},"hooks":{},"indexes":[],"uniques":[],"checks":[],"concurrencyCheckKeys":{},"className":"List","path":"./src/lists/list.entity.ts","collection":"lists","name":"List","abstract":false,"constructorParams":[],"toJsonParams":[],"extends":"BaseEntity","useCache":true,"relations":[{"name":"createdBy","reference":"m:1","cascade":["persist"],"type":"User","owner":true,"array":false}]},"origin":"./src/lists/list.entity.ts","hash":"e5f2bd565dc102205516159973c50b67","version":"5.6.16"}
